attrkid/__init__.py
attrkid/constants.py
attrkid/exceptions.py
attrkid/fields.py
attrkid/kind.py
attrkid/options.py
attrkid/reflect.py
attrkid/serde.py
attrkid/validators.py
tests/__init__.py
tests/test_kind.py
tests/test_serde.py
tests/test_validators.py
attrkid-0.9.0.dist-info/LICENSE
attrkid-0.9.0.dist-info/METADATA
attrkid-0.9.0.dist-info/WHEEL
attrkid-0.9.0.dist-info/top_level.txt
attrkid-0.9.0.dist-info/RECORD
